{
  "template": "https://github.com/ecmwf-projects/cookiecutter-conda-package",
  "commit": "8329975706fe45568991c997f9cedb3186e578ce",
  "checkout": null,
  "context": {
    "cookiecutter": {
      "project_name": "callcache",
      "project_slug": "callcache",
      "project_short_description": "Efficiently cache calls to functions",
      "copyright_holder": "B-Open Solutions srl",
      "copyright_year": "2019",
      "_template": "https://github.com/ecmwf-projects/cookiecutter-conda-package"
    }
  },
  "directory": null
}
